README.rst
setup.py
SparrowSDK.egg-info/PKG-INFO
SparrowSDK.egg-info/SOURCES.txt
SparrowSDK.egg-info/dependency_links.txt
SparrowSDK.egg-info/requires.txt
SparrowSDK.egg-info/top_level.txt
bin/sparrowsms
sparrowsms/__init__.py
sparrowsms/pushclient.py
sparrowsms/settings.py
sparrowsms/utils.py
test/test_sending_sms.py