Metadata-Version: 1.0
Name: SparrowSDK
Version: 1.0.1
Summary: Python SDK for Sparrow SMS API.
Home-page: http://api.sparrowsms.com/
Author: Sparrow SMS
Author-email: developers@sparrowsms.com
License: UNKNOWN
Platform: UNKNOWN
